pytuq/__init__.py
pytuq/fit/__init__.py
pytuq/fit/fit.py
pytuq/fit/gp.py
pytuq/func/__init__.py
pytuq/func/benchmark.py
pytuq/func/chem.py
pytuq/func/func.py
pytuq/func/genz.py
pytuq/func/oper.py
pytuq/func/poly.py
pytuq/func/toy.py
pytuq/gsa/__init__.py
pytuq/gsa/gsa.py
pytuq/linred/__init__.py
pytuq/linred/kle.py
pytuq/linred/klnn.py
pytuq/linred/klsurr.py
pytuq/linred/linred.py
pytuq/linred/svd.py
pytuq/lreg/__init__.py
pytuq/lreg/anl.py
pytuq/lreg/bcs.py
pytuq/lreg/lreg.py
pytuq/lreg/merr.py
pytuq/lreg/opt.py
pytuq/minf/__init__.py
pytuq/minf/calib.py
pytuq/minf/infer.py
pytuq/minf/likelihoods.py
pytuq/minf/mcmc.py
pytuq/minf/minf.py
pytuq/minf/priors.py
pytuq/minf/vi.py
pytuq/optim/__init__.py
pytuq/optim/gd.py
pytuq/optim/optim.py
pytuq/optim/pso.py
pytuq/optim/sciwrap.py
pytuq/rv/__init__.py
pytuq/rv/mrv.py
pytuq/rv/pcrv.py
pytuq/rv/rosen.py
pytuq/surrogates/__init__.py
pytuq/surrogates/nn.py
pytuq/surrogates/pce.py
pytuq/utils/__init__.py
pytuq/utils/decors.py
pytuq/utils/funcbank.py
pytuq/utils/integr.py
pytuq/utils/maps.py
pytuq/utils/metrics.py
pytuq/utils/mindex.py
pytuq/utils/plotting.py
pytuq/utils/stats.py
pytuq/utils/uqtk_utils.py
pytuq/utils/xutils.py
pytuq/workflows/__init__.py
pytuq/workflows/fits.py
pytuq/workflows/uprop.py
pytuq-1.0.0.dist-info/licenses/LICENSE.txt
pytuq-1.0.0.dist-info/METADATA
pytuq-1.0.0.dist-info/WHEEL
pytuq-1.0.0.dist-info/top_level.txt
pytuq-1.0.0.dist-info/RECORD
