Metadata-Version: 2.4
Name: pytuq
Version: 1.0.0
Summary: Python-only set of tools for uncertainty quantification.
Author: Khachik Sargsyan, Bert Debusschere
Maintainer: Emilie Grace Baillo
License: BSD 3-Clause License
Project-URL: Homepage, https://sandialabs.github.io/pytuq/
Project-URL: Repository, https://github.com/sandialabs/pytuq
Project-URL: Documentation, https://sandialabs.github.io/pytuq/
Keywords: uncertainty quantification
Classifier: Programming Language :: Python :: 3
Classifier: Programming Language :: Python :: 3.10
Classifier: Programming Language :: Python :: 3.11
Classifier: Programming Language :: Python :: 3.12
Classifier: Programming Language :: Python :: 3.13
Classifier: Programming Language :: Python :: 3 :: Only
Classifier: Intended Audience :: Science/Research
Classifier: Topic :: Scientific/Engineering :: Mathematics
Classifier: Natural Language :: English
Classifier: Operating System :: Unix
Classifier: Operating System :: MacOS
Requires-Python: >=3.8
License-File: LICENSE.txt
Requires-Dist: numpy
Requires-Dist: scipy
Requires-Dist: matplotlib
Provides-Extra: dev
Requires-Dist: pytest>=7.0; extra == "dev"
Requires-Dist: pytest-cov; extra == "dev"
Provides-Extra: nn
Requires-Dist: torch; extra == "nn"
Requires-Dist: uqinn; extra == "nn"
Provides-Extra: optim
Requires-Dist: pyswarms; extra == "optim"
Provides-Extra: all
Requires-Dist: torch; extra == "all"
Requires-Dist: uqinn; extra == "all"
Requires-Dist: pyswarms; extra == "all"
Dynamic: license-file
